picsl_image_graph_cut.pypy310-pp73-x86_64-linux-gnu.so
picsl_image_graph_cut-0.0.1.dist-info/RECORD
picsl_image_graph_cut-0.0.1.dist-info/METADATA
picsl_image_graph_cut-0.0.1.dist-info/WHEEL
picsl_image_graph_cut-0.0.1.dist-info/licenses/LICENSE
picsl_image_graph_cut.libs/libgomp-a34b3233.so.1.0.0
picsl_image_graph_cut.libs/libmetis-abd0e9f4.so.0
