Metadata-Version: 2.1
Name: picsl_image_graph_cut
Version: 0.0.1
Summary: PICSL Image Graph Cut: Graph Partitioning for Binary Image Volumes
Author-Email: "Paul A. Yushkevich" <pyushkevich@gmail.com>
Maintainer-Email: "Paul A. Yushkevich" <pyushkevich@gmail.com>
License:                     GNU GENERAL PUBLIC LICENSE
Classifier: Development Status :: 4 - Beta
Classifier: License :: OSI Approved :: BSD License
Classifier: Programming Language :: Python :: 3 :: Only
Classifier: Programming Language :: Python :: 3.8
Classifier: Programming Language :: Python :: 3.9
Classifier: Programming Language :: Python :: 3.10
Classifier: Programming Language :: Python :: 3.11
Classifier: Programming Language :: Python :: 3.12
Classifier: Topic :: Scientific/Engineering :: Physics
Project-URL: Homepage, https://github.com/pyushkevich/image-graph-cut
Requires-Python: >=3.8
Requires-Dist: typing_extensions
Requires-Dist: SimpleITK
Requires-Dist: numpy
